triviayaml.py
trivia_yaml-0.0.1.dist-info/DESCRIPTION.rst
trivia_yaml-0.0.1.dist-info/METADATA
trivia_yaml-0.0.1.dist-info/RECORD
trivia_yaml-0.0.1.dist-info/WHEEL
trivia_yaml-0.0.1.dist-info/entry_points.txt
trivia_yaml-0.0.1.dist-info/metadata.json
trivia_yaml-0.0.1.dist-info/namespace_packages.txt
trivia_yaml-0.0.1.dist-info/top_level.txt
