Metadata-Version: 2.0
Name: trivia-yaml
Version: 0.0.1
Summary: Convert Red's V2 trivia lists to YAML
Home-page: https://github.com/Tobotimus/trivia-yaml
Author: Tobotimus
Author-email: UNKNOWN
License: MIT
Platform: UNKNOWN
Requires-Dist: chardet
Requires-Dist: PyYAML
